MANIFEST.in
gcli.py
setup.cfg
setup.py
dir/LICENSE
dir/Python.gitignore
dir/__init__.py
gcli.egg-info/PKG-INFO
gcli.egg-info/SOURCES.txt
gcli.egg-info/dependency_links.txt
gcli.egg-info/entry_points.txt
gcli.egg-info/not-zip-safe
gcli.egg-info/top_level.txt