Metadata-Version: 1.0
Name: gcli
Version: 0.0.1
Summary: Automatically generate .gitignore/readme/license files cli
Home-page: https://github.com/chenjiandongx/gcli
Author: chenjiandongx
Author-email: chenjiandongx@qq.com
License: MIT
Keywords: git,cli
Platform: UNKNOWN
